mqt/qudits/__init__.py
mqt/qudits/_qudits.cpython-314-x86_64-linux-gnu.so
mqt/qudits/_version.py
mqt/qudits/_version.pyi
mqt/qudits/py.typed
mqt/qudits/_qudits/__init__.pyi
mqt/qudits/_qudits/misim.pyi
mqt/qudits/compiler/__init__.py
mqt/qudits/compiler/compiler_pass.py
mqt/qudits/compiler/dit_compiler.py
mqt/qudits/compiler/compilation_minitools/__init__.py
mqt/qudits/compiler/compilation_minitools/local_compilation_minitools.py
mqt/qudits/compiler/compilation_minitools/naive_unitary_verifier.py
mqt/qudits/compiler/compilation_minitools/numerical_ansatz_utils.py
mqt/qudits/compiler/naive_local_resynth/__init__.py
mqt/qudits/compiler/naive_local_resynth/local_resynth.py
mqt/qudits/compiler/onedit/__init__.py
mqt/qudits/compiler/onedit/local_operation_swap/__init__.py
mqt/qudits/compiler/onedit/local_operation_swap/swap_routine.py
mqt/qudits/compiler/onedit/local_phases_transpilation/__init__.py
mqt/qudits/compiler/onedit/local_phases_transpilation/propagate_virtrz.py
mqt/qudits/compiler/onedit/local_phases_transpilation/remove_phase_rotations.py
mqt/qudits/compiler/onedit/mapping_aware_transpilation/__init__.py
mqt/qudits/compiler/onedit/mapping_aware_transpilation/phy_local_adaptive_decomp.py
mqt/qudits/compiler/onedit/mapping_aware_transpilation/phy_local_qr_decomp.py
mqt/qudits/compiler/onedit/mapping_un_aware_transpilation/__init__.py
mqt/qudits/compiler/onedit/mapping_un_aware_transpilation/log_local_adaptive_decomp.py
mqt/qudits/compiler/onedit/mapping_un_aware_transpilation/log_local_qr_decomp.py
mqt/qudits/compiler/state_compilation/__init__.py
mqt/qudits/compiler/state_compilation/retrieve_state.py
mqt/qudits/compiler/state_compilation/state_preparation.py
mqt/qudits/compiler/twodit/__init__.py
mqt/qudits/compiler/twodit/blocks/__init__.py
mqt/qudits/compiler/twodit/blocks/crot.py
mqt/qudits/compiler/twodit/blocks/czrot.py
mqt/qudits/compiler/twodit/blocks/pswap.py
mqt/qudits/compiler/twodit/entanglement_qr/__init__.py
mqt_qudits-0.4.0.dist-info/METADATA
mqt_qudits-0.4.0.dist-info/WHEEL
mqt_qudits-0.4.0.dist-info/RECORD
mqt_qudits-0.4.0.dist-info/licenses/LICENSE.md
