Metadata-Version: 2.2
Name: mqt.qudits
Version: 0.4.0
Summary: A Framework For Mixed-Dimensional Qudit Quantum Computing
Keywords: MQT,quantum-computing,design-automation,qudits
Author-Email: Kevin Mato <kevin.mato@tum.de>, Lukas Burgholzer <lukas.burgholzer@tum.de>
License: MIT License
Classifier: Topic :: Scientific/Engineering :: Electronic Design Automation (EDA)
Classifier: Intended Audience :: Science/Research
Classifier: Natural Language :: English
Classifier: Operating System :: POSIX :: Linux
Classifier: Operating System :: MacOS
Classifier: Operating System :: Microsoft :: Windows
Classifier: License :: OSI Approved :: MIT License
Classifier: Programming Language :: C++
Classifier: Programming Language :: Python
Classifier: Programming Language :: Python :: 3
Classifier: Programming Language :: Python :: 3 :: Only
Classifier: Programming Language :: Python :: 3.10
Classifier: Programming Language :: Python :: 3.11
Classifier: Programming Language :: Python :: 3.12
Classifier: Programming Language :: Python :: 3.13
Classifier: Development Status :: 4 - Beta
Classifier: Typing :: Typed
Project-URL: Homepage, https://github.com/munich-quantum-toolkit/qudits
Project-URL: Documentation, https://mqt.readthedocs.io/projects/qudits
Project-URL: Issues, https://github.com/munich-quantum-toolkit/qudits/issues
Project-URL: Discussions, https://github.com/munich-quantum-toolkit/qudits/discussions
Requires-Python: >=3.10
Requires-Dist: numpy>=1.24; python_version < "3.12"
Requires-Dist: numpy>=1.26; python_version >= "3.12"
Requires-Dist: numpy>=2.1; python_version >= "3.13"
Requires-Dist: numpy>=2.3.2; python_version >= "3.14"
Requires-Dist: networkx>=3.0
Requires-Dist: scipy>=1.10; python_version < "3.12"
Requires-Dist: scipy>=1.12; python_version >= "3.12"
Requires-Dist: scipy>=1.15; python_version >= "3.13"
Requires-Dist: scipy>=1.16.1; python_version >= "3.14"
Requires-Dist: h5py>=3.8; python_version >= "3.11"
Requires-Dist: h5py>=3.12.1; python_version >= "3.12"
Requires-Dist: h5py>=3.15.0; python_version >= "3.14"
Requires-Dist: tensornetwork>=0.4
Requires-Dist: matplotlib>=3.7; python_version < "3.12"
Requires-Dist: matplotlib>=3.8; python_version >= "3.12"
Requires-Dist: matplotlib>=3.10; python_version >= "3.13"
Requires-Dist: matplotlib>=3.10.5; python_version >= "3.14"
Requires-Dist: typing-extensions>=4.1
